justpath/__init__.py
justpath/oneliners.py
justpath/show.py
justpath-0.0.18.dist-info/LICENSE
justpath-0.0.18.dist-info/METADATA
justpath-0.0.18.dist-info/WHEEL
justpath-0.0.18.dist-info/entry_points.txt
justpath-0.0.18.dist-info/RECORD
