Metadata-Version: 2.1
Name: justpath
Version: 0.0.18
Summary: Explore PATH environment variable on Windows and Linux.
Home-page: https://github.com/epogrebnyak/justpath
License: GNU
Author: Evgeny Pogrebnyak
Author-email: e.pogrebnyak@gmail.com
Requires-Python: >=3.10,<4.0
Classifier: License :: Other/Proprietary License
Classifier: Programming Language :: Python :: 3
Classifier: Programming Language :: Python :: 3.10
Classifier: Programming Language :: Python :: 3.11
Classifier: Programming Language :: Python :: 3.12
Classifier: Programming Language :: Python :: 3.13
Requires-Dist: colorama (>=0.4.6,<0.5.0)
Requires-Dist: typer (>=0.18.0,<0.19.0)
Requires-Dist: types-colorama (>=0.4.15.20240106,<0.5.0.0)
Project-URL: Repository, https://github.com/epogrebnyak/justpath
